README
setup.py
oshift/__init__.py
pyopenshift.egg-info/PKG-INFO
pyopenshift.egg-info/SOURCES.txt
pyopenshift.egg-info/dependency_links.txt
pyopenshift.egg-info/requires.txt
pyopenshift.egg-info/top_level.txt
tests/__init__.py
tests/apps.py
tests/domain.py
tests/user.py