Metadata-Version: 1.0
Name: pyopenshift
Version: 0.1
Summary: This is a python interface for the new Openshift REST API.
Home-page: https://github.com/openshift/python-interface
Author: Peter Ruan
Author-email: pruan@redhat.com
License: Unknown
Keywords: PaaS Redhat OpenShift
Platform: UNKNOWN
